coin_clicker/__init__.py
coin_clicker/__main__.py
coin_clicker/settings.py
coin_clicker-1.0.8.dist-info/WHEEL
coin_clicker-1.0.8.dist-info/METADATA
coin_clicker-1.0.8.dist-info/RECORD
