Metadata-Version: 2.1
Name: coin-clicker
Version: 1.0.8
Summary: Auto-clicks telegram crypto-bot websites to earn money.
Home-page: https://github.com/lee-hodg/coin-clicker
License: MIT
Keywords: LTC,Telegram,Automate,Crypto,Click
Author: lee
Author-email: lee@logicon.io
Maintainer: lee
Maintainer-email: lee@logicon.io
Requires-Python: >=3.6,<4.0
Classifier: License :: OSI Approved :: MIT License
Classifier: Programming Language :: Python :: 3
Classifier: Programming Language :: Python :: 3.6
Classifier: Programming Language :: Python :: 3.7
Classifier: Programming Language :: Python :: 3.8
Classifier: Programming Language :: Python :: 3.9
Requires-Dist: PyInquirer (>=1.0.3,<2.0.0)
Requires-Dist: Telethon (>=1.18.2,<2.0.0)
Requires-Dist: asyncio (>=3.4.3,<4.0.0)
Requires-Dist: bs4 (>=0.0.1,<0.0.2)
Requires-Dist: colorama (>=0.4.4,<0.5.0)
Requires-Dist: coloredlogs (>=15.0,<16.0)
Requires-Dist: pyfiglet (>=0.8.post1,<0.9)
Requires-Dist: requests (>=2.25.1,<3.0.0)
Project-URL: Repository, https://github.com/lee-hodg/coin-clicker
